README.md
setup.py
container_cron/__init__.py
container_cron/__main__.py
container_cron.egg-info/PKG-INFO
container_cron.egg-info/SOURCES.txt
container_cron.egg-info/dependency_links.txt
container_cron.egg-info/entry_points.txt
container_cron.egg-info/requires.txt
container_cron.egg-info/top_level.txt