Metadata-Version: 2.1
Name: container-cron
Version: 0.5.2
Summary: An automated service importing scheduled jobs from /etc/cron.d in running containers.
Home-page: https://github.com/iamfat/container-cron
Author: Jia Huang
Author-email: iamfat@gmail.com
License: MIT
Platform: UNKNOWN
Classifier: License :: OSI Approved :: MIT License
Classifier: Programming Language :: Python
Classifier: Programming Language :: Python :: 3
Classifier: Programming Language :: Python :: 3.5
Classifier: Programming Language :: Python :: 3.6
Classifier: Programming Language :: Python :: 3.7
Classifier: Programming Language :: Python :: Implementation :: CPython
Classifier: Programming Language :: Python :: Implementation :: PyPy
Requires-Python: >=3.5
